release/__init__.py
release/cli/__init__.py
release/cli/bump.py
release/cli/helpers.py
release/cli/main.py
release/constants.py
release/core.py
release/exceptions.py
ez_release-0.1.2.dist-info/WHEEL
ez_release-0.1.2.dist-info/entry_points.txt
ez_release-0.1.2.dist-info/METADATA
ez_release-0.1.2.dist-info/RECORD
