Metadata-Version: 2.1
Name: ez-release
Version: 0.1.2
Summary: Make release easier with git and semver tags.
Author: dithyrambe
Requires-Python: >=3.8,<3.12
Classifier: Programming Language :: Python :: 3
Classifier: Programming Language :: Python :: 3.8
Classifier: Programming Language :: Python :: 3.9
Classifier: Programming Language :: Python :: 3.10
Classifier: Programming Language :: Python :: 3.11
Requires-Dist: gitpython (>=3.1.31,<4.0.0)
Requires-Dist: pydantic (>=1.10.5,<2.0.0)
Requires-Dist: pyyaml (>=6.0,<7.0)
Requires-Dist: semver (>=2.13.0,<3.0.0)
Requires-Dist: typer[all] (>=0.7.0,<0.8.0)
